LICENSE
MANIFEST.in
README.rst
setup.cfg
setup.py
dictalchemy/__init__.py
dictalchemy/classes.py
dictalchemy/constants.py
dictalchemy/errors.py
dictalchemy/utils.py
dictalchemy/tests/__init__.py
dictalchemy/tests/test_asdict.py
dictalchemy/tests/test_fromdict.py
dictalchemy/tests/test_utils.py
dictalchemy3.egg-info/PKG-INFO
dictalchemy3.egg-info/SOURCES.txt
dictalchemy3.egg-info/dependency_links.txt
dictalchemy3.egg-info/not-zip-safe
dictalchemy3.egg-info/requires.txt
dictalchemy3.egg-info/top_level.txt